AUTHORS
LICENSE
MANIFEST.in
README.md
setup.py
django_admin_jobs/__init__.py
django_admin_jobs/__init__.pyc
django_admin_jobs/admin.py
django_admin_jobs/admin.pyc
django_admin_jobs/apps.py
django_admin_jobs/models.py
django_admin_jobs/task_pool.py
django_admin_jobs/tests.py
django_admin_jobs/tests.pyc
django_admin_jobs.egg-info/PKG-INFO
django_admin_jobs.egg-info/SOURCES.txt
django_admin_jobs.egg-info/dependency_links.txt
django_admin_jobs.egg-info/requires.txt
django_admin_jobs.egg-info/top_level.txt
django_admin_jobs/management/__init__.py
django_admin_jobs/management/__init__.pyc
django_admin_jobs/management/commands/__init__.py
django_admin_jobs/management/commands/run_upload_jobs.py
django_admin_jobs/migrations/0001_initial.py
django_admin_jobs/migrations/0001_initial.pyc
django_admin_jobs/migrations/__init__.py
django_admin_jobs/migrations/__init__.pyc
django_admin_jobs/static/django-admin-jobs/js/monitor.js
django_admin_jobs/static/django-admin-jobs/js/firebase/firebase-4.2.0.min.js
django_admin_jobs/static/django-admin-jobs/js/firebase/firebase-listener.js
django_admin_jobs/templates/admin/django_admin_jobs/upload_job/change_list.html
django_admin_jobs/templatetags/__init__.py
django_admin_jobs/templatetags/__init__.pyc
django_admin_jobs/templatetags/upload_tools_filters.py
django_admin_jobs/templatetags/upload_tools_filters.pyc